setup.py
myo/__coconut__.py
myo/__init__.py
myo/command.py
myo/dispatch.py
myo/env.py
myo/logging.py
myo/record.py
myo/settings.py
myo/view.py
myo.egg-info/PKG-INFO
myo.egg-info/SOURCES.txt
myo.egg-info/dependency_links.txt
myo.egg-info/requires.txt
myo.egg-info/top_level.txt
myo/components/__init__.py
myo/components/command/__init__.py
myo/components/command/main.py
myo/components/command/message.py
myo/components/command/util.py
myo/components/core/__init__.py
myo/components/core/dispatch.py
myo/components/core/main.py
myo/components/core/message.py
myo/components/tmux/__init__.py
myo/components/tmux/dispatch.py
myo/components/tmux/main.py
myo/components/tmux/message.py
myo/components/tmux/watcher.py
myo/components/unite/__init__.py
myo/components/unite/data.py
myo/components/unite/format.py
myo/components/unite/main.py
myo/components/unite/message.py
myo/output/__init__.py
myo/output/data.py
myo/output/machine.py
myo/output/main.py
myo/output/message.py
myo/output/filter/__init__.py
myo/output/filter/base.py
myo/output/parser/__init__.py
myo/output/parser/base.py
myo/output/parser/python.py
myo/output/parser/sbt.py
myo/output/reifier/__init__.py
myo/output/reifier/base.py
myo/output/reifier/python.py
myo/output/reifier/sbt.py
myo/output/syntax/__init__.py
myo/output/syntax/base.py
myo/output/syntax/python.py
myo/output/syntax/sbt.py
myo/test/__init__.py
myo/test/spec.py
myo/ui/__init__.py
myo/ui/tmux/__init__.py
myo/ui/tmux/adapter.py
myo/ui/tmux/data.py
myo/ui/tmux/layout.py
myo/ui/tmux/pack.py
myo/ui/tmux/pane.py
myo/ui/tmux/server.py
myo/ui/tmux/session.py
myo/ui/tmux/util.py
myo/ui/tmux/view.py
myo/ui/tmux/view_path.py
myo/ui/tmux/window.py
myo/ui/tmux/facade/__init__.py
myo/ui/tmux/facade/main.py
myo/ui/tmux/facade/window.py
myo/util/__init__.py
myo/util/ident.py