Metadata-Version: 1.0
Name: myo
Version: 0.36.1
Summary: command and layout management for neovim
Home-page: https://github.com/tek/myo
Author: Torsten Schmits
Author-email: torstenschmits@gmail.com
License: MIT
Platform: UNKNOWN
